advtorchattacks/__init__.py
advtorchattacks/autoattack.py
advtorchattacks/cw.py
advtorchattacks/deepfool.py
advtorchattacks/fgsm.py
advtorchattacks/mifgsm.py
advtorchattacks/pgd.py
models/__init__.py
models/attack_model.py
models/train_eval.py
advtorchattacks-2.1.1.dist-info/METADATA
advtorchattacks-2.1.1.dist-info/WHEEL
advtorchattacks-2.1.1.dist-info/top_level.txt
advtorchattacks-2.1.1.dist-info/RECORD
