Metadata-Version: 2.2
Name: advtorchattacks
Version: 2.1.1
Summary: A PyTorch library for adversarial attacks, inspired by torchattacks.
Home-page: https://github.com/santhos1705kumar/advtorchattacks
Author: Santhoshkumar K
Author-email: santhoshatwork17@gmail.com
Classifier: Programming Language :: Python :: 3
Classifier: License :: OSI Approved :: MIT License
Classifier: Operating System :: OS Independent
Classifier: Topic :: Scientific/Engineering :: Artificial Intelligence
Requires-Python: >=3.7
Requires-Dist: torch>=1.8.0
Requires-Dist: torchvision
Requires-Dist: numpy
Requires-Dist: scipy
Dynamic: author
Dynamic: author-email
Dynamic: classifier
Dynamic: description
Dynamic: description-content-type
Dynamic: home-page
Dynamic: requires-dist
Dynamic: requires-python
Dynamic: summary
